MANIFEST.in
README.rst
requirements.txt
setup.py
fulltext/__init__.py
fulltext/util.py
fulltext.egg-info/PKG-INFO
fulltext.egg-info/SOURCES.txt
fulltext.egg-info/dependency_links.txt
fulltext.egg-info/requires.txt
fulltext.egg-info/top_level.txt
fulltext/backends/__csv.py
fulltext/backends/__doc.py
fulltext/backends/__docx.py
fulltext/backends/__html.py
fulltext/backends/__init__.py
fulltext/backends/__odt.py
fulltext/backends/__pdf.py
fulltext/backends/__pptx.py
fulltext/backends/__rtf.py
fulltext/backends/__text.py
fulltext/backends/__xlsx.py
fulltext/backends/__xml.py
fulltext/backends/__zip.py