Metadata-Version: 1.1
Name: fulltext
Version: 0.5
Summary: Convert binary files to plain text for indexing.
Home-page: http://github.com/btimby/fulltext/
Author: Ben Timby
Author-email: btimby@gmail.com
License: GPLv3
Platform: UNKNOWN
Classifier: Development Status :: 4 - Beta
Classifier: Intended Audience :: Developers
Classifier: Operating System :: OS Independent
Classifier: Programming Language :: Python
Classifier: Topic :: Software Development :: Libraries :: Python Modules
Classifier: Topic :: Text Processing :: Indexing
